datacatalog_tag_manager/__init__.py
datacatalog_tag_manager/constant.py
datacatalog_tag_manager/datacatalog_entity_factory.py
datacatalog_tag_manager/datacatalog_facade.py
datacatalog_tag_manager/tag_datasource_processor.py
datacatalog_tag_manager/tag_manager_cli.py
datacatalog_tag_manager-2.2.0.dist-info/LICENSE
datacatalog_tag_manager-2.2.0.dist-info/METADATA
datacatalog_tag_manager-2.2.0.dist-info/WHEEL
datacatalog_tag_manager-2.2.0.dist-info/entry_points.txt
datacatalog_tag_manager-2.2.0.dist-info/top_level.txt
datacatalog_tag_manager-2.2.0.dist-info/RECORD
