Metadata-Version: 2.1
Name: datacatalog-tag-manager
Version: 2.2.0
Summary: A package to manage Google Cloud Data Catalog tags, loading metadata from external sources
Home-page: https://github.com/ricardolsmendes/datacatalog-tag-manager
Author: Ricardo Mendes
Author-email: ricardolsmendes@gmail.com
License: MIT
Platform: Posix; MacOS X; Windows
Classifier: Development Status :: 3 - Alpha
Classifier: License :: OSI Approved :: MIT License
Classifier: Natural Language :: English
Classifier: Operating System :: OS Independent
Classifier: Programming Language :: Python
Classifier: Programming Language :: Python :: 3.6
Classifier: Programming Language :: Python :: 3.7
Classifier: Programming Language :: Python :: 3.8
Requires-Python: >=3.6
Requires-Dist: google-cloud-datacatalog (~=3.0)
Requires-Dist: numpy (<=1.19.3,>=1.19.0)
Requires-Dist: pandas (~=1.1.4)
